AUTHORS.rst
CHANGELOG.rst
LICENSE
MANIFEST.in
README.rst
setup.py
arrange/__init__.py
arrange/admin.py
arrange/managers.py
arrange/models.py
arrange/signal_handlers.py
arrange/utils.py
arrange/templates/admin/arrange/change_list.html
arrange/templates/arrange/arrange_change_list.html
django_arrange.egg-info/PKG-INFO
django_arrange.egg-info/SOURCES.txt
django_arrange.egg-info/dependency_links.txt
django_arrange.egg-info/not-zip-safe
django_arrange.egg-info/top_level.txt