Metadata-Version: 1.0
Name: django-arrange
Version: 0.0.3
Summary: Django app providing arbitrary, admin user specified, object arranging.
Home-page: http://github.com/praekelt/django-arrange
Author: Praekelt Foundation
Author-email: dev@praekelt.com
License: BSD
Platform: UNKNOWN
Classifier: Programming Language :: Python
Classifier: License :: OSI Approved :: BSD License
Classifier: Development Status :: 4 - Beta
Classifier: Operating System :: OS Independent
Classifier: Framework :: Django
Classifier: Intended Audience :: Developers
Classifier: Topic :: Internet :: WWW/HTTP :: Dynamic Content
